strfry/__init__.py
strfry/main.py
StrFry-1.0.0.dist-info/LICENSE
StrFry-1.0.0.dist-info/METADATA
StrFry-1.0.0.dist-info/WHEEL
StrFry-1.0.0.dist-info/top_level.txt
StrFry-1.0.0.dist-info/RECORD
