Metadata-Version: 2.1
Name: StrFry
Version: 1.0.0
Summary: The easiest way to create human-readable tables in Python!
Home-page: https://github.com/LucasHaefner/StrFry
Author: Lucas Haefner
Author-email: lucashaefner360@gmail.com
License: MIT
Download-URL: https://github.com/LucasHaefner/StrFry/archive/v1.0.0.tar.gz
Keywords: String,Str,Dunder,Special Method,Table,Tables,Data,List,Iterable
Platform: UNKNOWN
Classifier: Programming Language :: Python :: 3
Classifier: Development Status :: 4 - Beta
Classifier: Intended Audience :: Developers
Classifier: Topic :: Software Development :: Build Tools
Classifier: License :: OSI Approved :: MIT License
Classifier: Operating System :: OS Independent
Requires-Python: >=3.0
